upgradeable_streams/__init__.py
upgradeable_streams/client.py
upgradeable_streams/protocol.py
upgradeable_streams/py.typed
upgradeable_streams/server.py
upgradeable_streams/writer.py
jetblack_upgradeable_streams-0.3.0.dist-info/WHEEL
jetblack_upgradeable_streams-0.3.0.dist-info/METADATA
jetblack_upgradeable_streams-0.3.0.dist-info/RECORD
