Metadata-Version: 2.1
Name: jetblack-upgradeable-streams
Version: 0.3.0
Summary: An experiment in upgradeable streams
Home-page: https://github.com/rob-blackbourn/asyncio-upgradeable-streams
License: Apache-2.0
Author: Rob Blackbourn
Author-email: rob.blackbourn@gmail.com
Requires-Python: >=3.8,<4.0
Classifier: License :: OSI Approved :: Apache Software License
Classifier: Programming Language :: Python :: 3
Classifier: Programming Language :: Python :: 3.10
Classifier: Programming Language :: Python :: 3.8
Classifier: Programming Language :: Python :: 3.9
Project-URL: Repository, https://github.com/rob-blackbourn/asyncio-upgradeable-streams
